bytebridge/__init__.py
bytebridge/cli.py
bytebridge/exceptions.py
bytebridge/operations.py
bytebridge/parsers.py
bytebridge/connectors/__init__.py
bytebridge/connectors/base.py
bytebridge/connectors/database.py
bytebridge/connectors/file.py
bytebridge-0.0.3.dist-info/entry_points.txt
bytebridge-0.0.3.dist-info/LICENSE
bytebridge-0.0.3.dist-info/WHEEL
bytebridge-0.0.3.dist-info/METADATA
bytebridge-0.0.3.dist-info/RECORD
