Metadata-Version: 2.1
Name: bytebridge
Version: 0.0.3
Summary: A data tool designed to move data seamlessly between various sources and destinations.
Author-email: Rafael Vargas <contact@rafaelvargas.dev>
Requires-Python: >=3.7
Requires-Dist: psycopg[binary] >=3.0.9
Requires-Dist: pyarrow >=7.0.0
Requires-Dist: mysql-connector-python >=8.0.19
Requires-Dist: pymssql >=2.2.11
Requires-Dist: ruff ==0.1.5 ; extra == "dev"
Requires-Dist: pre-commit >=2.17.0 ; extra == "dev"
Requires-Dist: pytest ==8.1.1 ; extra == "dev"
Provides-Extra: dev
